{"v":"5.8.1","fr":30,"ip":0,"op":151,"w":375,"h":50,"nm":"progress bar","ddd":0,"assets":[],"layers":[{"ddd":0,"ind":1,"ty":3,"nm":"Null 3","sr":1,"ks":{"o":{"a":0,"k":0,"ix":11},"r":{"a":0,"k":0,"ix":10},"p":{"a":0,"k":[187.5,-356,0],"ix":2,"l":2},"a":{"a":0,"k":[0,0,0],"ix":1,"l":2},"s":{"a":0,"k":[100,100,100],"ix":6,"l":2}},"ao":0,"ip":0,"op":300,"st":0,"bm":0},{"ddd":0,"ind":2,"ty":4,"nm":"Shape Layer 3","parent":1,"sr":1,"ks":{"o":{"a":0,"k":100,"ix":11},"r":{"a":0,"k":0,"ix":10},"p":{"k":[{"s":[-20.499,380.909,0],"t":1,"i":{"x":1,"y":1},"o":{"x":0,"y":0}},{"s":[-20.497,380.58,0],"t":2,"i":{"x":1,"y":1},"o":{"x":0,"y":0}},{"s":[-20.491,379.965,0],"t":3,"i":{"x":1,"y":1},"o":{"x":0,"y":0}},{"s":[-20.483,378.973,0],"t":4,"i":{"x":1,"y":1},"o":{"x":0,"y":0}},{"s":[-20.471,377.438,0],"t":5,"i":{"x":1,"y":1},"o":{"x":0,"y":0}},{"s":[-20.452,375.139,0],"t":6,"i":{"x":1,"y":1},"o":{"x":0,"y":0}},{"s":[-20.426,371.958,0],"t":7,"i":{"x":1,"y":1},"o":{"x":0,"y":0}},{"s":[-20.398,368.573,0],"t":8,"i":{"x":1,"y":1},"o":{"x":0,"y":0}},{"s":[-20.381,366.545,0],"t":9,"i":{"x":1,"y":1},"o":{"x":0,"y":0}},{"s":[-20.377,366,0],"t":10,"i":{"x":1,"y":1},"o":{"x":0,"y":0}},{"s":[-20.377,366.091,0],"t":11,"i":{"x":1,"y":1},"o":{"x":0,"y":0}},{"s":[-20.38,366.418,0],"t":12,"i":{"x":1,"y":1},"o":{"x":0,"y":0}},{"s":[-20.385,367.032,0],"t":13,"i":{"x":1,"y":1},"o":{"x":0,"y":0}},{"s":[-20.393,368.027,0],"t":14,"i":{"x":1,"y":1},"o":{"x":0,"y":0}},{"s":[-20.406,369.561,0],"t":15,"i":{"x":1,"y":1},"o":{"x":0,"y":0}},{"s":[-20.425,371.847,0],"t":16,"i":{"x":1,"y":1},"o":{"x":0,"y":0}},{"s":[-20.451,375.027,0],"t":17,"i":{"x":1,"y":1},"o":{"x":0,"y":0}},{"s":[-20.479,378.427,0],"t":18,"i":{"x":1,"y":1},"o":{"x":0,"y":0}},{"s":[-20.495,380.452,0],"t":19,"i":{"x":1,"y":1},"o":{"x":0,"y":0}},{"s":[-20.5,381,0],"t":20,"i":{"x":1,"y":1},"o":{"x":0,"y":0}},{"s":[-20.499,380.909,0],"t":31,"i":{"x":1,"y":1},"o":{"x":0,"y":0}},{"s":[-20.497,380.58,0],"t":32,"i":{"x":1,"y":1},"o":{"x":0,"y":0}},{"s":[-20.491,379.965,0],"t":33,"i":{"x":1,"y":1},"o":{"x":0,"y":0}},{"s":[-20.483,378.973,0],"t":34,"i":{"x":1,"y":1},"o":{"x":0,"y":0}},{"s":[-20.471,377.438,0],"t":35,"i":{"x":1,"y":1},"o":{"x":0,"y":0}},{"s":[-20.452,375.139,0],"t":36,"i":{"x":1,"y":1},"o":{"x":0,"y":0}},{"s":[-20.426,371.958,0],"t":37,"i":{"x":1,"y":1},"o":{"x":0,"y":0}},{"s":[-20.398,368.573,0],"t":38,"i":{"x":1,"y":1},"o":{"x":0,"y":0}},{"s":[-20.381,366.545,0],"t":39,"i":{"x":1,"y":1},"o":{"x":0,"y":0}},{"s":[-20.377,366,0],"t":40,"i":{"x":1,"y":1},"o":{"x":0,"y":0}},{"s":[-20.377,366.091,0],"t":41,"i":{"x":1,"y":1},"o":{"x":0,"y":0}},{"s":[-20.38,366.418,0],"t":42,"i":{"x":1,"y":1},"o":{"x":0,"y":0}},{"s":[-20.385,367.032,0],"t":43,"i":{"x":1,"y":1},"o":{"x":0,"y":0}},{"s":[-20.393,368.027,0],"t":44,"i":{"x":1,"y":1},"o":{"x":0,"y":0}},{"s":[-20.406,369.561,0],"t":45,"i":{"x":1,"y":1},"o":{"x":0,"y":0}},{"s":[-20.425,371.847,0],"t":46,"i":{"x":1,"y":1},"o":{"x":0,"y":0}},{"s":[-20.451,375.027,0],"t":47,"i":{"x":1,"y":1},"o":{"x":0,"y":0}},{"s":[-20.479,378.427,0],"t":48,"i":{"x":1,"y":1},"o":{"x":0,"y":0}},{"s":[-20.495,380.452,0],"t":49,"i":{"x":1,"y":1},"o":{"x":0,"y":0}},{"s":[-20.5,381,0],"t":50,"i":{"x":1,"y":1},"o":{"x":0,"y":0}},{"s":[-20.499,380.909,0],"t":61,"i":{"x":1,"y":1},"o":{"x":0,"y":0}},{"s":[-20.497,380.58,0],"t":62,"i":{"x":1,"y":1},"o":{"x":0,"y":0}},{"s":[-20.491,379.965,0],"t":63,"i":{"x":1,"y":1},"o":{"x":0,"y":0}},{"s":[-20.483,378.973,0],"t":64,"i":{"x":1,"y":1},"o":{"x":0,"y":0}},{"s":[-20.471,377.438,0],"t":65,"i":{"x":1,"y":1},"o":{"x":0,"y":0}},{"s":[-20.452,375.139,0],"t":66,"i":{"x":1,"y":1},"o":{"x":0,"y":0}},{"s":[-20.426,371.958,0],"t":67,"i":{"x":1,"y":1},"o":{"x":0,"y":0}},{"s":[-20.398,368.573,0],"t":68,"i":{"x":1,"y":1},"o":{"x":0,"y":0}},{"s":[-20.381,366.545,0],"t":69,"i":{"x":1,"y":1},"o":{"x":0,"y":0}},{"s":[-20.377,366,0],"t":70,"i":{"x":1,"y":1},"o":{"x":0,"y":0}},{"s":[-20.377,366.091,0],"t":71,"i":{"x":1,"y":1},"o":{"x":0,"y":0}},{"s":[-20.38,366.418,0],"t":72,"i":{"x":1,"y":1},"o":{"x":0,"y":0}},{"s":[-20.385,367.032,0],"t":73,"i":{"x":1,"y":1},"o":{"x":0,"y":0}},{"s":[-20.393,368.027,0],"t":74,"i":{"x":1,"y":1},"o":{"x":0,"y":0}},{"s":[-20.406,369.561,0],"t":75,"i":{"x":1,"y":1},"o":{"x":0,"y":0}},{"s":[-20.425,371.847,0],"t":76,"i":{"x":1,"y":1},"o":{"x":0,"y":0}},{"s":[-20.451,375.027,0],"t":77,"i":{"x":1,"y":1},"o":{"x":0,"y":0}},{"s":[-20.479,378.427,0],"t":78,"i":{"x":1,"y":1},"o":{"x":0,"y":0}},{"s":[-20.495,380.452,0],"t":79,"i":{"x":1,"y":1},"o":{"x":0,"y":0}},{"s":[-20.5,381,0],"t":80,"i":{"x":1,"y":1},"o":{"x":0,"y":0}},{"s":[-20.499,380.909,0],"t":91,"i":{"x":1,"y":1},"o":{"x":0,"y":0}},{"s":[-20.497,380.58,0],"t":92,"i":{"x":1,"y":1},"o":{"x":0,"y":0}},{"s":[-20.491,379.965,0],"t":93,"i":{"x":1,"y":1},"o":{"x":0,"y":0}},{"s":[-20.483,378.973,0],"t":94,"i":{"x":1,"y":1},"o":{"x":0,"y":0}},{"s":[-20.471,377.438,0],"t":95,"i":{"x":1,"y":1},"o":{"x":0,"y":0}},{"s":[-20.452,375.139,0],"t":96,"i":{"x":1,"y":1},"o":{"x":0,"y":0}},{"s":[-20.426,371.958,0],"t":97,"i":{"x":1,"y":1},"o":{"x":0,"y":0}},{"s":[-20.398,368.573,0],"t":98,"i":{"x":1,"y":1},"o":{"x":0,"y":0}},{"s":[-20.381,366.545,0],"t":99,"i":{"x":1,"y":1},"o":{"x":0,"y":0}},{"s":[-20.377,366,0],"t":100,"i":{"x":1,"y":1},"o":{"x":0,"y":0}},{"s":[-20.377,366.091,0],"t":101,"i":{"x":1,"y":1},"o":{"x":0,"y":0}},{"s":[-20.38,366.418,0],"t":102,"i":{"x":1,"y":1},"o":{"x":0,"y":0}},{"s":[-20.385,367.032,0],"t":103,"i":{"x":1,"y":1},"o":{"x":0,"y":0}},{"s":[-20.393,368.027,0],"t":104,"i":{"x":1,"y":1},"o":{"x":0,"y":0}},{"s":[-20.406,369.561,0],"t":105,"i":{"x":1,"y":1},"o":{"x":0,"y":0}},{"s":[-20.425,371.847,0],"t":106,"i":{"x":1,"y":1},"o":{"x":0,"y":0}},{"s":[-20.451,375.027,0],"t":107,"i":{"x":1,"y":1},"o":{"x":0,"y":0}},{"s":[-20.479,378.427,0],"t":108,"i":{"x":1,"y":1},"o":{"x":0,"y":0}},{"s":[-20.495,380.452,0],"t":109,"i":{"x":1,"y":1},"o":{"x":0,"y":0}},{"s":[-20.5,381,0],"t":110,"i":{"x":1,"y":1},"o":{"x":0,"y":0}},{"s":[-20.499,380.909,0],"t":121,"i":{"x":1,"y":1},"o":{"x":0,"y":0}},{"s":[-20.497,380.58,0],"t":122,"i":{"x":1,"y":1},"o":{"x":0,"y":0}},{"s":[-20.491,379.965,0],"t":123,"i":{"x":1,"y":1},"o":{"x":0,"y":0}},{"s":[-20.483,378.973,0],"t":124,"i":{"x":1,"y":1},"o":{"x":0,"y":0}},{"s":[-20.471,377.438,0],"t":125,"i":{"x":1,"y":1},"o":{"x":0,"y":0}},{"s":[-20.452,375.139,0],"t":126,"i":{"x":1,"y":1},"o":{"x":0,"y":0}},{"s":[-20.426,371.958,0],"t":127,"i":{"x":1,"y":1},"o":{"x":0,"y":0}},{"s":[-20.398,368.573,0],"t":128,"i":{"x":1,"y":1},"o":{"x":0,"y":0}},{"s":[-20.381,366.545,0],"t":129,"i":{"x":1,"y":1},"o":{"x":0,"y":0}},{"s":[-20.377,366,0],"t":130,"i":{"x":1,"y":1},"o":{"x":0,"y":0}},{"s":[-20.377,366.091,0],"t":131,"i":{"x":1,"y":1},"o":{"x":0,"y":0}},{"s":[-20.38,366.418,0],"t":132,"i":{"x":1,"y":1},"o":{"x":0,"y":0}},{"s":[-20.385,367.032,0],"t":133,"i":{"x":1,"y":1},"o":{"x":0,"y":0}},{"s":[-20.393,368.027,0],"t":134,"i":{"x":1,"y":1},"o":{"x":0,"y":0}},{"s":[-20.406,369.561,0],"t":135,"i":{"x":1,"y":1},"o":{"x":0,"y":0}},{"s":[-20.425,371.847,0],"t":136,"i":{"x":1,"y":1},"o":{"x":0,"y":0}},{"s":[-20.451,375.027,0],"t":137,"i":{"x":1,"y":1},"o":{"x":0,"y":0}},{"s":[-20.479,378.427,0],"t":138,"i":{"x":1,"y":1},"o":{"x":0,"y":0}},{"s":[-20.495,380.452,0],"t":139,"i":{"x":1,"y":1},"o":{"x":0,"y":0}},{"s":[-20.5,381,0],"t":140,"i":{"x":1,"y":1},"o":{"x":0,"y":0}}],"l":2},"a":{"a":0,"k":[-147.96,-229.233,0],"ix":1,"l":2},"s":{"a":0,"k":[8,8,100],"ix":6,"l":2}},"ao":0,"shapes":[{"ty":"gr","it":[{"ind":0,"ty":"sh","ix":1,"ks":{"a":0,"k":{"i":[[31.058,0],[0,-31.058],[-31.058,0],[0,31.058]],"o":[[-31.058,0],[0,31.058],[31.058,0],[0,-31.058]],"v":[[0,-56.236],[-56.236,0],[0,56.236],[56.236,0]],"c":true},"ix":2},"nm":"Path 1","mn":"ADBE Vector Shape - Group","hd":false},{"ty":"st","c":{"a":0,"k":[0.984314024682,0.588234994926,0.439215985466,1],"ix":3},"o":{"a":0,"k":100,"ix":4},"w":{"a":0,"k":0,"ix":5},"lc":1,"lj":1,"ml":4,"bm":0,"nm":"Stroke 1","mn":"ADBE Vector Graphic - Stroke","hd":false},{"ty":"fl","c":{"a":0,"k":[0.980392217636,0.376470625401,0.152941182256,1],"ix":4},"o":{"a":0,"k":100,"ix":5},"r":1,"bm":0,"nm":"Fill 1","mn":"ADBE Vector Graphic - Fill","hd":false},{"ty":"tr","p":{"a":0,"k":[-97.96,-229.233],"ix":2},"a":{"a":0,"k":[0,0],"ix":1},"s":{"a":0,"k":[100,100],"ix":3},"r":{"a":0,"k":0,"ix":6},"o":{"a":0,"k":100,"ix":7},"sk":{"a":0,"k":0,"ix":4},"sa":{"a":0,"k":0,"ix":5},"nm":"Transform"}],"nm":"Ellipse 1","np":3,"cix":2,"bm":0,"ix":1,"mn":"ADBE Vector Group","hd":false}],"ip":0,"op":300,"st":0,"bm":0},{"ddd":0,"ind":3,"ty":4,"nm":"Shape Layer 2","parent":1,"sr":1,"ks":{"o":{"a":0,"k":100,"ix":11},"r":{"a":0,"k":0,"ix":10},"p":{"k":[{"s":[-0.5,381,0],"t":2,"i":{"x":1,"y":1},"o":{"x":0,"y":0}},{"s":[-0.499,380.909,0],"t":3,"i":{"x":1,"y":1},"o":{"x":0,"y":0}},{"s":[-0.497,380.58,0],"t":4,"i":{"x":1,"y":1},"o":{"x":0,"y":0}},{"s":[-0.491,379.965,0],"t":5,"i":{"x":1,"y":1},"o":{"x":0,"y":0}},{"s":[-0.483,378.973,0],"t":6,"i":{"x":1,"y":1},"o":{"x":0,"y":0}},{"s":[-0.471,377.438,0],"t":7,"i":{"x":1,"y":1},"o":{"x":0,"y":0}},{"s":[-0.452,375.139,0],"t":8,"i":{"x":1,"y":1},"o":{"x":0,"y":0}},{"s":[-0.426,371.958,0],"t":9,"i":{"x":1,"y":1},"o":{"x":0,"y":0}},{"s":[-0.398,368.573,0],"t":10,"i":{"x":1,"y":1},"o":{"x":0,"y":0}},{"s":[-0.381,366.545,0],"t":11,"i":{"x":1,"y":1},"o":{"x":0,"y":0}},{"s":[-0.377,366,0],"t":12,"i":{"x":1,"y":1},"o":{"x":0,"y":0}},{"s":[-0.377,366.091,0],"t":13,"i":{"x":1,"y":1},"o":{"x":0,"y":0}},{"s":[-0.38,366.418,0],"t":14,"i":{"x":1,"y":1},"o":{"x":0,"y":0}},{"s":[-0.385,367.032,0],"t":15,"i":{"x":1,"y":1},"o":{"x":0,"y":0}},{"s":[-0.393,368.027,0],"t":16,"i":{"x":1,"y":1},"o":{"x":0,"y":0}},{"s":[-0.406,369.561,0],"t":17,"i":{"x":1,"y":1},"o":{"x":0,"y":0}},{"s":[-0.425,371.847,0],"t":18,"i":{"x":1,"y":1},"o":{"x":0,"y":0}},{"s":[-0.451,375.027,0],"t":19,"i":{"x":1,"y":1},"o":{"x":0,"y":0}},{"s":[-0.479,378.427,0],"t":20,"i":{"x":1,"y":1},"o":{"x":0,"y":0}},{"s":[-0.495,380.452,0],"t":21,"i":{"x":1,"y":1},"o":{"x":0,"y":0}},{"s":[-0.5,381,0],"t":22,"i":{"x":1,"y":1},"o":{"x":0,"y":0}},{"s":[-0.5,381,0],"t":32,"i":{"x":1,"y":1},"o":{"x":0,"y":0}},{"s":[-0.499,380.909,0],"t":33,"i":{"x":1,"y":1},"o":{"x":0,"y":0}},{"s":[-0.497,380.58,0],"t":34,"i":{"x":1,"y":1},"o":{"x":0,"y":0}},{"s":[-0.491,379.965,0],"t":35,"i":{"x":1,"y":1},"o":{"x":0,"y":0}},{"s":[-0.483,378.973,0],"t":36,"i":{"x":1,"y":1},"o":{"x":0,"y":0}},{"s":[-0.471,377.438,0],"t":37,"i":{"x":1,"y":1},"o":{"x":0,"y":0}},{"s":[-0.452,375.139,0],"t":38,"i":{"x":1,"y":1},"o":{"x":0,"y":0}},{"s":[-0.426,371.958,0],"t":39,"i":{"x":1,"y":1},"o":{"x":0,"y":0}},{"s":[-0.398,368.573,0],"t":40,"i":{"x":1,"y":1},"o":{"x":0,"y":0}},{"s":[-0.381,366.545,0],"t":41,"i":{"x":1,"y":1},"o":{"x":0,"y":0}},{"s":[-0.377,366,0],"t":42,"i":{"x":1,"y":1},"o":{"x":0,"y":0}},{"s":[-0.377,366.091,0],"t":43,"i":{"x":1,"y":1},"o":{"x":0,"y":0}},{"s":[-0.38,366.418,0],"t":44,"i":{"x":1,"y":1},"o":{"x":0,"y":0}},{"s":[-0.385,367.032,0],"t":45,"i":{"x":1,"y":1},"o":{"x":0,"y":0}},{"s":[-0.393,368.027,0],"t":46,"i":{"x":1,"y":1},"o":{"x":0,"y":0}},{"s":[-0.406,369.561,0],"t":47,"i":{"x":1,"y":1},"o":{"x":0,"y":0}},{"s":[-0.425,371.847,0],"t":48,"i":{"x":1,"y":1},"o":{"x":0,"y":0}},{"s":[-0.451,375.027,0],"t":49,"i":{"x":1,"y":1},"o":{"x":0,"y":0}},{"s":[-0.479,378.427,0],"t":50,"i":{"x":1,"y":1},"o":{"x":0,"y":0}},{"s":[-0.495,380.452,0],"t":51,"i":{"x":1,"y":1},"o":{"x":0,"y":0}},{"s":[-0.5,381,0],"t":52,"i":{"x":1,"y":1},"o":{"x":0,"y":0}},{"s":[-0.5,381,0],"t":62,"i":{"x":1,"y":1},"o":{"x":0,"y":0}},{"s":[-0.499,380.909,0],"t":63,"i":{"x":1,"y":1},"o":{"x":0,"y":0}},{"s":[-0.497,380.58,0],"t":64,"i":{"x":1,"y":1},"o":{"x":0,"y":0}},{"s":[-0.491,379.965,0],"t":65,"i":{"x":1,"y":1},"o":{"x":0,"y":0}},{"s":[-0.483,378.973,0],"t":66,"i":{"x":1,"y":1},"o":{"x":0,"y":0}},{"s":[-0.471,377.438,0],"t":67,"i":{"x":1,"y":1},"o":{"x":0,"y":0}},{"s":[-0.452,375.139,0],"t":68,"i":{"x":1,"y":1},"o":{"x":0,"y":0}},{"s":[-0.426,371.958,0],"t":69,"i":{"x":1,"y":1},"o":{"x":0,"y":0}},{"s":[-0.398,368.573,0],"t":70,"i":{"x":1,"y":1},"o":{"x":0,"y":0}},{"s":[-0.381,366.545,0],"t":71,"i":{"x":1,"y":1},"o":{"x":0,"y":0}},{"s":[-0.377,366,0],"t":72,"i":{"x":1,"y":1},"o":{"x":0,"y":0}},{"s":[-0.377,366.091,0],"t":73,"i":{"x":1,"y":1},"o":{"x":0,"y":0}},{"s":[-0.38,366.418,0],"t":74,"i":{"x":1,"y":1},"o":{"x":0,"y":0}},{"s":[-0.385,367.032,0],"t":75,"i":{"x":1,"y":1},"o":{"x":0,"y":0}},{"s":[-0.393,368.027,0],"t":76,"i":{"x":1,"y":1},"o":{"x":0,"y":0}},{"s":[-0.406,369.561,0],"t":77,"i":{"x":1,"y":1},"o":{"x":0,"y":0}},{"s":[-0.425,371.847,0],"t":78,"i":{"x":1,"y":1},"o":{"x":0,"y":0}},{"s":[-0.451,375.027,0],"t":79,"i":{"x":1,"y":1},"o":{"x":0,"y":0}},{"s":[-0.479,378.427,0],"t":80,"i":{"x":1,"y":1},"o":{"x":0,"y":0}},{"s":[-0.495,380.452,0],"t":81,"i":{"x":1,"y":1},"o":{"x":0,"y":0}},{"s":[-0.5,381,0],"t":82,"i":{"x":1,"y":1},"o":{"x":0,"y":0}},{"s":[-0.5,381,0],"t":92,"i":{"x":1,"y":1},"o":{"x":0,"y":0}},{"s":[-0.499,380.909,0],"t":93,"i":{"x":1,"y":1},"o":{"x":0,"y":0}},{"s":[-0.497,380.58,0],"t":94,"i":{"x":1,"y":1},"o":{"x":0,"y":0}},{"s":[-0.491,379.965,0],"t":95,"i":{"x":1,"y":1},"o":{"x":0,"y":0}},{"s":[-0.483,378.973,0],"t":96,"i":{"x":1,"y":1},"o":{"x":0,"y":0}},{"s":[-0.471,377.438,0],"t":97,"i":{"x":1,"y":1},"o":{"x":0,"y":0}},{"s":[-0.452,375.139,0],"t":98,"i":{"x":1,"y":1},"o":{"x":0,"y":0}},{"s":[-0.426,371.958,0],"t":99,"i":{"x":1,"y":1},"o":{"x":0,"y":0}},{"s":[-0.398,368.573,0],"t":100,"i":{"x":1,"y":1},"o":{"x":0,"y":0}},{"s":[-0.381,366.545,0],"t":101,"i":{"x":1,"y":1},"o":{"x":0,"y":0}},{"s":[-0.377,366,0],"t":102,"i":{"x":1,"y":1},"o":{"x":0,"y":0}},{"s":[-0.377,366.091,0],"t":103,"i":{"x":1,"y":1},"o":{"x":0,"y":0}},{"s":[-0.38,366.418,0],"t":104,"i":{"x":1,"y":1},"o":{"x":0,"y":0}},{"s":[-0.385,367.032,0],"t":105,"i":{"x":1,"y":1},"o":{"x":0,"y":0}},{"s":[-0.393,368.027,0],"t":106,"i":{"x":1,"y":1},"o":{"x":0,"y":0}},{"s":[-0.406,369.561,0],"t":107,"i":{"x":1,"y":1},"o":{"x":0,"y":0}},{"s":[-0.425,371.847,0],"t":108,"i":{"x":1,"y":1},"o":{"x":0,"y":0}},{"s":[-0.451,375.027,0],"t":109,"i":{"x":1,"y":1},"o":{"x":0,"y":0}},{"s":[-0.479,378.427,0],"t":110,"i":{"x":1,"y":1},"o":{"x":0,"y":0}},{"s":[-0.495,380.452,0],"t":111,"i":{"x":1,"y":1},"o":{"x":0,"y":0}},{"s":[-0.5,381,0],"t":112,"i":{"x":1,"y":1},"o":{"x":0,"y":0}},{"s":[-0.5,381,0],"t":122,"i":{"x":1,"y":1},"o":{"x":0,"y":0}},{"s":[-0.499,380.909,0],"t":123,"i":{"x":1,"y":1},"o":{"x":0,"y":0}},{"s":[-0.497,380.58,0],"t":124,"i":{"x":1,"y":1},"o":{"x":0,"y":0}},{"s":[-0.491,379.965,0],"t":125,"i":{"x":1,"y":1},"o":{"x":0,"y":0}},{"s":[-0.483,378.973,0],"t":126,"i":{"x":1,"y":1},"o":{"x":0,"y":0}},{"s":[-0.471,377.438,0],"t":127,"i":{"x":1,"y":1},"o":{"x":0,"y":0}},{"s":[-0.452,375.139,0],"t":128,"i":{"x":1,"y":1},"o":{"x":0,"y":0}},{"s":[-0.426,371.958,0],"t":129,"i":{"x":1,"y":1},"o":{"x":0,"y":0}},{"s":[-0.398,368.573,0],"t":130,"i":{"x":1,"y":1},"o":{"x":0,"y":0}},{"s":[-0.381,366.545,0],"t":131,"i":{"x":1,"y":1},"o":{"x":0,"y":0}},{"s":[-0.377,366,0],"t":132,"i":{"x":1,"y":1},"o":{"x":0,"y":0}},{"s":[-0.377,366.091,0],"t":133,"i":{"x":1,"y":1},"o":{"x":0,"y":0}},{"s":[-0.38,366.418,0],"t":134,"i":{"x":1,"y":1},"o":{"x":0,"y":0}},{"s":[-0.385,367.032,0],"t":135,"i":{"x":1,"y":1},"o":{"x":0,"y":0}},{"s":[-0.393,368.027,0],"t":136,"i":{"x":1,"y":1},"o":{"x":0,"y":0}},{"s":[-0.406,369.561,0],"t":137,"i":{"x":1,"y":1},"o":{"x":0,"y":0}},{"s":[-0.425,371.847,0],"t":138,"i":{"x":1,"y":1},"o":{"x":0,"y":0}},{"s":[-0.451,375.027,0],"t":139,"i":{"x":1,"y":1},"o":{"x":0,"y":0}},{"s":[-0.479,378.427,0],"t":140,"i":{"x":1,"y":1},"o":{"x":0,"y":0}},{"s":[-0.495,380.452,0],"t":141,"i":{"x":1,"y":1},"o":{"x":0,"y":0}},{"s":[-0.5,381,0],"t":142,"i":{"x":1,"y":1},"o":{"x":0,"y":0}}],"l":2},"a":{"a":0,"k":[-97.96,-229.233,0],"ix":1,"l":2},"s":{"a":0,"k":[8,8,100],"ix":6,"l":2}},"ao":0,"shapes":[{"ty":"gr","it":[{"ind":0,"ty":"sh","ix":1,"ks":{"a":0,"k":{"i":[[31.058,0],[0,-31.058],[-31.058,0],[0,31.058]],"o":[[-31.058,0],[0,31.058],[31.058,0],[0,-31.058]],"v":[[0,-56.236],[-56.236,0],[0,56.236],[56.236,0]],"c":true},"ix":2},"nm":"Path 1","mn":"ADBE Vector Shape - Group","hd":false},{"ty":"st","c":{"a":0,"k":[0.984314024682,0.588234994926,0.439215985466,1],"ix":3},"o":{"a":0,"k":100,"ix":4},"w":{"a":0,"k":0,"ix":5},"lc":1,"lj":1,"ml":4,"bm":0,"nm":"Stroke 1","mn":"ADBE Vector Graphic - Stroke","hd":false},{"ty":"fl","c":{"a":0,"k":[0.980392217636,0.376470625401,0.152941182256,1],"ix":4},"o":{"a":0,"k":100,"ix":5},"r":1,"bm":0,"nm":"Fill 1","mn":"ADBE Vector Graphic - Fill","hd":false},{"ty":"tr","p":{"a":0,"k":[-97.96,-229.233],"ix":2},"a":{"a":0,"k":[0,0],"ix":1},"s":{"a":0,"k":[100,100],"ix":3},"r":{"a":0,"k":0,"ix":6},"o":{"a":0,"k":100,"ix":7},"sk":{"a":0,"k":0,"ix":4},"sa":{"a":0,"k":0,"ix":5},"nm":"Transform"}],"nm":"Ellipse 1","np":3,"cix":2,"bm":0,"ix":1,"mn":"ADBE Vector Group","hd":false}],"ip":0,"op":300,"st":0,"bm":0},{"ddd":0,"ind":4,"ty":4,"nm":"Shape Layer 4","parent":1,"sr":1,"ks":{"o":{"a":0,"k":100,"ix":11},"r":{"a":0,"k":0,"ix":10},"p":{"k":[{"s":[19.501,380.909,0],"t":5,"i":{"x":1,"y":1},"o":{"x":0,"y":0}},{"s":[19.503,380.58,0],"t":6,"i":{"x":1,"y":1},"o":{"x":0,"y":0}},{"s":[19.509,379.965,0],"t":7,"i":{"x":1,"y":1},"o":{"x":0,"y":0}},{"s":[19.517,378.973,0],"t":8,"i":{"x":1,"y":1},"o":{"x":0,"y":0}},{"s":[19.529,377.438,0],"t":9,"i":{"x":1,"y":1},"o":{"x":0,"y":0}},{"s":[19.548,375.139,0],"t":10,"i":{"x":1,"y":1},"o":{"x":0,"y":0}},{"s":[19.574,371.958,0],"t":11,"i":{"x":1,"y":1},"o":{"x":0,"y":0}},{"s":[19.602,368.573,0],"t":12,"i":{"x":1,"y":1},"o":{"x":0,"y":0}},{"s":[19.619,366.545,0],"t":13,"i":{"x":1,"y":1},"o":{"x":0,"y":0}},{"s":[19.623,366,0],"t":14,"i":{"x":1,"y":1},"o":{"x":0,"y":0}},{"s":[19.623,366.091,0],"t":15,"i":{"x":1,"y":1},"o":{"x":0,"y":0}},{"s":[19.62,366.418,0],"t":16,"i":{"x":1,"y":1},"o":{"x":0,"y":0}},{"s":[19.615,367.032,0],"t":17,"i":{"x":1,"y":1},"o":{"x":0,"y":0}},{"s":[19.607,368.027,0],"t":18,"i":{"x":1,"y":1},"o":{"x":0,"y":0}},{"s":[19.594,369.561,0],"t":19,"i":{"x":1,"y":1},"o":{"x":0,"y":0}},{"s":[19.575,371.847,0],"t":20,"i":{"x":1,"y":1},"o":{"x":0,"y":0}},{"s":[19.549,375.027,0],"t":21,"i":{"x":1,"y":1},"o":{"x":0,"y":0}},{"s":[19.521,378.427,0],"t":22,"i":{"x":1,"y":1},"o":{"x":0,"y":0}},{"s":[19.505,380.452,0],"t":23,"i":{"x":1,"y":1},"o":{"x":0,"y":0}},{"s":[19.5,381,0],"t":24,"i":{"x":1,"y":1},"o":{"x":0,"y":0}},{"s":[19.501,380.909,0],"t":35,"i":{"x":1,"y":1},"o":{"x":0,"y":0}},{"s":[19.503,380.58,0],"t":36,"i":{"x":1,"y":1},"o":{"x":0,"y":0}},{"s":[19.509,379.965,0],"t":37,"i":{"x":1,"y":1},"o":{"x":0,"y":0}},{"s":[19.517,378.973,0],"t":38,"i":{"x":1,"y":1},"o":{"x":0,"y":0}},{"s":[19.529,377.438,0],"t":39,"i":{"x":1,"y":1},"o":{"x":0,"y":0}},{"s":[19.548,375.139,0],"t":40,"i":{"x":1,"y":1},"o":{"x":0,"y":0}},{"s":[19.574,371.958,0],"t":41,"i":{"x":1,"y":1},"o":{"x":0,"y":0}},{"s":[19.602,368.573,0],"t":42,"i":{"x":1,"y":1},"o":{"x":0,"y":0}},{"s":[19.619,366.545,0],"t":43,"i":{"x":1,"y":1},"o":{"x":0,"y":0}},{"s":[19.623,366,0],"t":44,"i":{"x":1,"y":1},"o":{"x":0,"y":0}},{"s":[19.623,366.091,0],"t":45,"i":{"x":1,"y":1},"o":{"x":0,"y":0}},{"s":[19.62,366.418,0],"t":46,"i":{"x":1,"y":1},"o":{"x":0,"y":0}},{"s":[19.615,367.032,0],"t":47,"i":{"x":1,"y":1},"o":{"x":0,"y":0}},{"s":[19.607,368.027,0],"t":48,"i":{"x":1,"y":1},"o":{"x":0,"y":0}},{"s":[19.594,369.561,0],"t":49,"i":{"x":1,"y":1},"o":{"x":0,"y":0}},{"s":[19.575,371.847,0],"t":50,"i":{"x":1,"y":1},"o":{"x":0,"y":0}},{"s":[19.549,375.027,0],"t":51,"i":{"x":1,"y":1},"o":{"x":0,"y":0}},{"s":[19.521,378.427,0],"t":52,"i":{"x":1,"y":1},"o":{"x":0,"y":0}},{"s":[19.505,380.452,0],"t":53,"i":{"x":1,"y":1},"o":{"x":0,"y":0}},{"s":[19.5,381,0],"t":54,"i":{"x":1,"y":1},"o":{"x":0,"y":0}},{"s":[19.501,380.909,0],"t":65,"i":{"x":1,"y":1},"o":{"x":0,"y":0}},{"s":[19.503,380.58,0],"t":66,"i":{"x":1,"y":1},"o":{"x":0,"y":0}},{"s":[19.509,379.965,0],"t":67,"i":{"x":1,"y":1},"o":{"x":0,"y":0}},{"s":[19.517,378.973,0],"t":68,"i":{"x":1,"y":1},"o":{"x":0,"y":0}},{"s":[19.529,377.438,0],"t":69,"i":{"x":1,"y":1},"o":{"x":0,"y":0}},{"s":[19.548,375.139,0],"t":70,"i":{"x":1,"y":1},"o":{"x":0,"y":0}},{"s":[19.574,371.958,0],"t":71,"i":{"x":1,"y":1},"o":{"x":0,"y":0}},{"s":[19.602,368.573,0],"t":72,"i":{"x":1,"y":1},"o":{"x":0,"y":0}},{"s":[19.619,366.545,0],"t":73,"i":{"x":1,"y":1},"o":{"x":0,"y":0}},{"s":[19.623,366,0],"t":74,"i":{"x":1,"y":1},"o":{"x":0,"y":0}},{"s":[19.623,366.091,0],"t":75,"i":{"x":1,"y":1},"o":{"x":0,"y":0}},{"s":[19.62,366.418,0],"t":76,"i":{"x":1,"y":1},"o":{"x":0,"y":0}},{"s":[19.615,367.032,0],"t":77,"i":{"x":1,"y":1},"o":{"x":0,"y":0}},{"s":[19.607,368.027,0],"t":78,"i":{"x":1,"y":1},"o":{"x":0,"y":0}},{"s":[19.594,369.561,0],"t":79,"i":{"x":1,"y":1},"o":{"x":0,"y":0}},{"s":[19.575,371.847,0],"t":80,"i":{"x":1,"y":1},"o":{"x":0,"y":0}},{"s":[19.549,375.027,0],"t":81,"i":{"x":1,"y":1},"o":{"x":0,"y":0}},{"s":[19.521,378.427,0],"t":82,"i":{"x":1,"y":1},"o":{"x":0,"y":0}},{"s":[19.505,380.452,0],"t":83,"i":{"x":1,"y":1},"o":{"x":0,"y":0}},{"s":[19.5,381,0],"t":84,"i":{"x":1,"y":1},"o":{"x":0,"y":0}},{"s":[19.501,380.909,0],"t":95,"i":{"x":1,"y":1},"o":{"x":0,"y":0}},{"s":[19.503,380.58,0],"t":96,"i":{"x":1,"y":1},"o":{"x":0,"y":0}},{"s":[19.509,379.965,0],"t":97,"i":{"x":1,"y":1},"o":{"x":0,"y":0}},{"s":[19.517,378.973,0],"t":98,"i":{"x":1,"y":1},"o":{"x":0,"y":0}},{"s":[19.529,377.438,0],"t":99,"i":{"x":1,"y":1},"o":{"x":0,"y":0}},{"s":[19.548,375.139,0],"t":100,"i":{"x":1,"y":1},"o":{"x":0,"y":0}},{"s":[19.574,371.958,0],"t":101,"i":{"x":1,"y":1},"o":{"x":0,"y":0}},{"s":[19.602,368.573,0],"t":102,"i":{"x":1,"y":1},"o":{"x":0,"y":0}},{"s":[19.619,366.545,0],"t":103,"i":{"x":1,"y":1},"o":{"x":0,"y":0}},{"s":[19.623,366,0],"t":104,"i":{"x":1,"y":1},"o":{"x":0,"y":0}},{"s":[19.623,366.091,0],"t":105,"i":{"x":1,"y":1},"o":{"x":0,"y":0}},{"s":[19.62,366.418,0],"t":106,"i":{"x":1,"y":1},"o":{"x":0,"y":0}},{"s":[19.615,367.032,0],"t":107,"i":{"x":1,"y":1},"o":{"x":0,"y":0}},{"s":[19.607,368.027,0],"t":108,"i":{"x":1,"y":1},"o":{"x":0,"y":0}},{"s":[19.594,369.561,0],"t":109,"i":{"x":1,"y":1},"o":{"x":0,"y":0}},{"s":[19.575,371.847,0],"t":110,"i":{"x":1,"y":1},"o":{"x":0,"y":0}},{"s":[19.549,375.027,0],"t":111,"i":{"x":1,"y":1},"o":{"x":0,"y":0}},{"s":[19.521,378.427,0],"t":112,"i":{"x":1,"y":1},"o":{"x":0,"y":0}},{"s":[19.505,380.452,0],"t":113,"i":{"x":1,"y":1},"o":{"x":0,"y":0}},{"s":[19.5,381,0],"t":114,"i":{"x":1,"y":1},"o":{"x":0,"y":0}},{"s":[19.501,380.909,0],"t":125,"i":{"x":1,"y":1},"o":{"x":0,"y":0}},{"s":[19.503,380.58,0],"t":126,"i":{"x":1,"y":1},"o":{"x":0,"y":0}},{"s":[19.509,379.965,0],"t":127,"i":{"x":1,"y":1},"o":{"x":0,"y":0}},{"s":[19.517,378.973,0],"t":128,"i":{"x":1,"y":1},"o":{"x":0,"y":0}},{"s":[19.529,377.438,0],"t":129,"i":{"x":1,"y":1},"o":{"x":0,"y":0}},{"s":[19.548,375.139,0],"t":130,"i":{"x":1,"y":1},"o":{"x":0,"y":0}},{"s":[19.574,371.958,0],"t":131,"i":{"x":1,"y":1},"o":{"x":0,"y":0}},{"s":[19.602,368.573,0],"t":132,"i":{"x":1,"y":1},"o":{"x":0,"y":0}},{"s":[19.619,366.545,0],"t":133,"i":{"x":1,"y":1},"o":{"x":0,"y":0}},{"s":[19.623,366,0],"t":134,"i":{"x":1,"y":1},"o":{"x":0,"y":0}},{"s":[19.623,366.091,0],"t":135,"i":{"x":1,"y":1},"o":{"x":0,"y":0}},{"s":[19.62,366.418,0],"t":136,"i":{"x":1,"y":1},"o":{"x":0,"y":0}},{"s":[19.615,367.032,0],"t":137,"i":{"x":1,"y":1},"o":{"x":0,"y":0}},{"s":[19.607,368.027,0],"t":138,"i":{"x":1,"y":1},"o":{"x":0,"y":0}},{"s":[19.594,369.561,0],"t":139,"i":{"x":1,"y":1},"o":{"x":0,"y":0}},{"s":[19.575,371.847,0],"t":140,"i":{"x":1,"y":1},"o":{"x":0,"y":0}},{"s":[19.549,375.027,0],"t":141,"i":{"x":1,"y":1},"o":{"x":0,"y":0}},{"s":[19.521,378.427,0],"t":142,"i":{"x":1,"y":1},"o":{"x":0,"y":0}},{"s":[19.505,380.452,0],"t":143,"i":{"x":1,"y":1},"o":{"x":0,"y":0}},{"s":[19.5,381,0],"t":144,"i":{"x":1,"y":1},"o":{"x":0,"y":0}}],"l":2},"a":{"a":0,"k":[-47.96,-229.233,0],"ix":1,"l":2},"s":{"a":0,"k":[8,8,100],"ix":6,"l":2}},"ao":0,"shapes":[{"ty":"gr","it":[{"ind":0,"ty":"sh","ix":1,"ks":{"a":0,"k":{"i":[[31.058,0],[0,-31.058],[-31.058,0],[0,31.058]],"o":[[-31.058,0],[0,31.058],[31.058,0],[0,-31.058]],"v":[[0,-56.236],[-56.236,0],[0,56.236],[56.236,0]],"c":true},"ix":2},"nm":"Path 1","mn":"ADBE Vector Shape - Group","hd":false},{"ty":"st","c":{"a":0,"k":[0.984314024682,0.588234994926,0.439215985466,1],"ix":3},"o":{"a":0,"k":100,"ix":4},"w":{"a":0,"k":0,"ix":5},"lc":1,"lj":1,"ml":4,"bm":0,"nm":"Stroke 1","mn":"ADBE Vector Graphic - Stroke","hd":false},{"ty":"fl","c":{"a":0,"k":[0.980392217636,0.376470625401,0.152941182256,1],"ix":4},"o":{"a":0,"k":100,"ix":5},"r":1,"bm":0,"nm":"Fill 1","mn":"ADBE Vector Graphic - Fill","hd":false},{"ty":"tr","p":{"a":0,"k":[-97.96,-229.233],"ix":2},"a":{"a":0,"k":[0,0],"ix":1},"s":{"a":0,"k":[100,100],"ix":3},"r":{"a":0,"k":0,"ix":6},"o":{"a":0,"k":100,"ix":7},"sk":{"a":0,"k":0,"ix":4},"sa":{"a":0,"k":0,"ix":5},"nm":"Transform"}],"nm":"Ellipse 1","np":3,"cix":2,"bm":0,"ix":1,"mn":"ADBE Vector Group","hd":false}],"ip":0,"op":300,"st":0,"bm":0}],"markers":[]}